{
  "run_id": "run_76cf1dcf6fb8",
  "day_index": 4,
  "markers": [
    {
      "lat": 33.6055366,
      "lng": -117.9199016,
      "name": "뉴포트 비치 (Newport Beach)"
    },
    {
      "lat": 33.6069697,
      "lng": -117.8904793,
      "name": "발보아 아일랜드 (Balboa Island)"
    },
    {
      "lat": 33.6594835,
      "lng": -117.9988026,
      "name": "헌팅턴 비치 (Huntington Beach)"
    },
    {
      "lat": 33.942153,
      "lng": -118.4036052,
      "name": "로스앤젤레스 국제공항"
    }
  ],
  "path": [
    [
      33.60611,
      -117.91977
    ],
    [
      33.60626,
      -117.9207
    ],
    [
      33.60627,
      -117.9207
    ],
    [
      33.60628,
      -117.92086
    ],
    [
      33.60647,
      -117.9223
    ],
    [
      33.60668,
      -117.92367
    ],
    [
      33.60689,
      -117.9251
    ],
    [
      33.60692,
      -117.92509
    ],
    [
      33.60702,
      -117.9252
    ],
    [
      33.60754,
      -117.92509
    ],
    [
      33.60767,
      -117.92583
    ],
    [
      33.60771,
      -117.92605
    ],
    [
      33.60787,
      -117.92652
    ],
    [
      33.60804,
      -117.92689
    ],
    [
      33.60833,
      -117.92736
    ],
    [
      33.60855,
      -117.92762
    ],
    [
      33.60884,
      -117.92792
    ],
    [
      33.60883,
      -117.92793
    ],
    [
      33.60893,
      -117.92799
    ],
    [
      33.60911,
      -117.92814
    ],
    [
      33.60944,
      -117.92848
    ],
    [
      33.60945,
      -117.92852
    ],
    [
      33.60962,
      -117.92866
    ],
    [
      33.60962,
      -117.92873
    ],
    [
      33.61011,
      -117.92896
    ],
    [
      33.61014,
      -117.92893
    ],
    [
      33.61027,
      -117.92878
    ],
    [
      33.61032,
      -117.92877
    ],
    [
      33.61062,
      -117.92892
    ],
    [
      33.61083,
      -117.92902
    ],
    [
      33.61095,
      -117.92911
    ],
    [
      33.61094,
      -117.92912
    ],
    [
      33.61096,
      -117.92921
    ],
    [
      33.61213,
      -117.93017
    ],
    [
      33.61423,
      -117.93207
    ],
    [
      33.6148,
      -117.93251
    ],
    [
      33.62165,
      -117.93868
    ],
    [
      33.62201,
      -117.93892
    ],
    [
      33.62222,
      -117.93903
    ],
    [
      33.62272,
      -117.93925
    ],
    [
      33.62285,
      -117.93928
    ],
    [
      33.62315,
      -117.93901
    ],
    [
      33.62329,
      -117.93878
    ],
    [
      33.62337,
      -117.9385
    ],
    [
      33.6234,
      -117.93821
    ],
    [
      33.62332,
      -117.93685
    ],
    [
      33.62336,
      -117.93654
    ],
    [
      33.62348,
      -117.9362
    ],
    [
      33.62363,
      -117.93595
    ],
    [
      33.62442,
      -117.93518
    ],
    [
      33.62529,
      -117.9343
    ],
    [
      33.62584,
      -117.93376
    ],
    [
      33.62578,
      -117.9336
    ],
    [
      33.62577,
      -117.9315
    ],
    [
      33.62574,
      -117.93074
    ],
    [
      33.62795,
      -117.93183
    ],
    [
      33.62833,
      -117.93181
    ],
    [
      33.63955,
      -117.93195
    ],
    [
      33.63955,
      -117.93187
    ],
    [
      33.63955,
      -117.93184
    ],
    [
      33.63965,
      -117.93184
    ],
    [
      33.63965,
      -117.93207
    ],
    [
      33.63925,
      -117.93207
    ],
    [
      33.63925,
      -117.93208
    ],
    [
      33.63936,
      -117.93207
    ],
    [
      33.63936,
      -117.93195
    ],
    [
      33.63612,
      -117.93191
    ],
    [
      33.63619,
      -117.9247
    ],
    [
      33.63619,
      -117.92366
    ],
    [
      33.63612,
      -117.92361
    ],
    [
      33.6361,
      -117.92348
    ],
    [
      33.63617,
      -117.92289
    ],
    [
      33.63624,
      -117.92241
    ],
    [
      33.63628,
      -117.92199
    ],
    [
      33.63634,
      -117.92177
    ],
    [
      33.63641,
      -117.92125
    ],
    [
      33.6364,
      -117.92082
    ],
    [
      33.63638,
      -117.92062
    ],
    [
      33.63622,
      -117.92011
    ],
    [
      33.63617,
      -117.91987
    ],
    [
      33.63572,
      -117.91923
    ],
    [
      33.63565,
      -117.91909
    ],
    [
      33.6338,
      -117.91641
    ],
    [
      33.63263,
      -117.91478
    ],
    [
      33.63042,
      -117.91155
    ],
    [
      33.62853,
      -117.90883
    ],
    [
      33.62841,
      -117.90874
    ],
    [
      33.62831,
      -117.90861
    ],
    [
      33.62585,
      -117.90508
    ],
    [
      33.62551,
      -117.90461
    ],
    [
      33.62519,
      -117.90454
    ],
    [
      33.62502,
      -117.90457
    ],
    [
      33.62473,
      -117.90474
    ],
    [
      33.62436,
      -117.90515
    ],
    [
      33.62406,
      -117.90543
    ],
    [
      33.62374,
      -117.90565
    ],
    [
      33.62051,
      -117.90747
    ],
    [
      33.62016,
      -117.9076
    ],
    [
      33.61987,
      -117.90766
    ],
    [
      33.6195,
      -117.90765
    ],
    [
      33.61916,
      -117.9076
    ],
    [
      33.61883,
      -117.90748
    ],
    [
      33.61806,
      -117.90712
    ],
    [
      33.61773,
      -117.90704
    ],
    [
      33.61742,
      -117.90702
    ],
    [
      33.61711,
      -117.90708
    ],
    [
      33.61667,
      -117.90725
    ],
    [
      33.61633,
      -117.90728
    ],
    [
      33.6161,
      -117.90733
    ],
    [
      33.61624,
      -117.9068
    ],
    [
      33.61657,
      -117.90575
    ],
    [
      33.61667,
      -117.90528
    ],
    [
      33.61671,
      -117.90486
    ],
    [
      33.61671,
      -117.90427
    ],
    [
      33.61665,
      -117.90382
    ],
    [
      33.61657,
      -117.90342
    ],
    [
      33.61629,
      -117.90243
    ],
    [
      33.61623,
      -117.90196
    ],
    [
      33.61619,
      -117.90089
    ],
    [
      33.61434,
      -117.89984
    ],
    [
      33.61411,
      -117.89967
    ],
    [
      33.61317,
      -117.89864
    ],
    [
      33.61295,
      -117.89832
    ],
    [
      33.61222,
      -117.89694
    ],
    [
      33.61209,
      -117.89659
    ],
    [
      33.61204,
      -117.89642
    ],
    [
      33.61197,
      -117.89592
    ],
    [
      33.61191,
      -117.89525
    ],
    [
      33.61181,
      -117.89483
    ],
    [
      33.61166,
      -117.89444
    ],
    [
      33.61155,
      -117.89423
    ],
    [
      33.61109,
      -117.89351
    ],
    [
      33.61093,
      -117.89319
    ],
    [
      33.6108,
      -117.89274
    ],
    [
      33.61065,
      -117.89279
    ],
    [
      33.61051,
      -117.89279
    ],
    [
      33.61052,
      -117.89318
    ],
    [
      33.61065,
      -117.89321
    ],
    [
      33.6108,
      -117.89319
    ],
    [
      33.61068,
      -117.89277
    ],
    [
      33.61062,
      -117.8923
    ],
    [
      33.61048,
      -117.88995
    ],
    [
      33.61002,
      -117.88992
    ],
    [
      33.60978,
      -117.88988
    ],
    [
      33.60861,
      -117.88988
    ],
    [
      33.60862,
      -117.89048
    ],
    [
      33.60694,
      -117.89048
    ],
    [
      33.60694,
      -117.89048
    ],
    [
      33.60862,
      -117.89048
    ],
    [
      33.60861,
      -117.88988
    ],
    [
      33.60994,
      -117.88989
    ],
    [
      33.61034,
      -117.88995
    ],
    [
      33.61048,
      -117.88995
    ],
    [
      33.61048,
      -117.89003
    ],
    [
      33.61068,
      -117.89018
    ],
    [
      33.61069,
      -117.89031
    ],
    [
      33.61071,
      -117.89029
    ],
    [
      33.61071,
      -117.8905
    ],
    [
      33.61074,
      -117.89081
    ],
    [
      33.6107,
      -117.89081
    ],
    [
      33.61065,
      -117.89082
    ],
    [
      33.61076,
      -117.89252
    ],
    [
      33.61085,
      -117.89294
    ],
    [
      33.61096,
      -117.89325
    ],
    [
      33.61119,
      -117.89367
    ],
    [
      33.61155,
      -117.89423
    ],
    [
      33.61173,
      -117.8946
    ],
    [
      33.61188,
      -117.89507
    ],
    [
      33.61194,
      -117.89554
    ],
    [
      33.61197,
      -117.89592
    ],
    [
      33.61204,
      -117.89642
    ],
    [
      33.61218,
      -117.89686
    ],
    [
      33.61277,
      -117.898
    ],
    [
      33.61306,
      -117.89849
    ],
    [
      33.61326,
      -117.89875
    ],
    [
      33.61414,
      -117.89969
    ],
    [
      33.61449,
      -117.89994
    ],
    [
      33.61636,
      -117.90098
    ],
    [
      33.6164,
      -117.902
    ],
    [
      33.61647,
      -117.90246
    ],
    [
      33.61678,
      -117.90373
    ],
    [
      33.61684,
      -117.90434
    ],
    [
      33.61684,
      -117.90478
    ],
    [
      33.6168,
      -117.90529
    ],
    [
      33.61679,
      -117.90566
    ],
    [
      33.61658,
      -117.9065
    ],
    [
      33.61658,
      -117.90665
    ],
    [
      33.61664,
      -117.90678
    ],
    [
      33.61674,
      -117.90687
    ],
    [
      33.6169,
      -117.90688
    ],
    [
      33.61716,
      -117.90683
    ],
    [
      33.61727,
      -117.90687
    ],
    [
      33.61771,
      -117.90683
    ],
    [
      33.61799,
      -117.90687
    ],
    [
      33.61933,
      -117.90749
    ],
    [
      33.61964,
      -117.90755
    ],
    [
      33.61997,
      -117.90751
    ],
    [
      33.62036,
      -117.90738
    ],
    [
      33.62089,
      -117.9071
    ],
    [
      33.62374,
      -117.90549
    ],
    [
      33.62408,
      -117.90524
    ],
    [
      33.62461,
      -117.9047
    ],
    [
      33.62509,
      -117.90418
    ],
    [
      33.62513,
      -117.9041
    ],
    [
      33.62521,
      -117.90401
    ],
    [
      33.62629,
      -117.90552
    ],
    [
      33.62838,
      -117.90854
    ],
    [
      33.62849,
      -117.90865
    ],
    [
      33.62853,
      -117.90883
    ],
    [
      33.63161,
      -117.91327
    ],
    [
      33.63284,
      -117.91507
    ],
    [
      33.6338,
      -117.91641
    ],
    [
      33.6355,
      -117.91886
    ],
    [
      33.63567,
      -117.91912
    ],
    [
      33.63572,
      -117.91923
    ],
    [
      33.63617,
      -117.91987
    ],
    [
      33.63629,
      -117.91998
    ],
    [
      33.63638,
      -117.92011
    ],
    [
      33.63652,
      -117.92068
    ],
    [
      33.63654,
      -117.92121
    ],
    [
      33.63649,
      -117.92168
    ],
    [
      33.63637,
      -117.92242
    ],
    [
      33.63623,
      -117.92351
    ],
    [
      33.63619,
      -117.92366
    ],
    [
      33.63619,
      -117.92558
    ],
    [
      33.63612,
      -117.93191
    ],
    [
      33.64285,
      -117.93199
    ],
    [
      33.6431,
      -117.93198
    ],
    [
      33.6434,
      -117.93199
    ],
    [
      33.6434,
      -117.9302
    ],
    [
      33.64345,
      -117.92344
    ],
    [
      33.64338,
      -117.92331
    ],
    [
      33.64335,
      -117.92117
    ],
    [
      33.64337,
      -117.92075
    ],
    [
      33.64337,
      -117.92036
    ],
    [
      33.64335,
      -117.92018
    ],
    [
      33.64336,
      -117.91891
    ],
    [
      33.64342,
      -117.9189
    ],
    [
      33.64405,
      -117.91892
    ],
    [
      33.64421,
      -117.91899
    ],
    [
      33.6445,
      -117.91902
    ],
    [
      33.64932,
      -117.91905
    ],
    [
      33.64932,
      -117.91901
    ],
    [
      33.64932,
      -117.91905
    ],
    [
      33.65256,
      -117.91909
    ],
    [
      33.653,
      -117.91911
    ],
    [
      33.65314,
      -117.9191
    ],
    [
      33.6554,
      -117.91912
    ],
    [
      33.65541,
      -117.91906
    ],
    [
      33.65762,
      -117.91906
    ],
    [
      33.66313,
      -117.91909
    ],
    [
      33.67459,
      -117.91918
    ],
    [
      33.67945,
      -117.91923
    ],
    [
      33.68028,
      -117.91922
    ],
    [
      33.68427,
      -117.91929
    ],
    [
      33.68684,
      -117.9193
    ],
    [
      33.68734,
      -117.91928
    ],
    [
      33.68889,
      -117.91933
    ],
    [
      33.69159,
      -117.91935
    ],
    [
      33.69169,
      -117.91933
    ],
    [
      33.69375,
      -117.91937
    ],
    [
      33.69564,
      -117.9194
    ],
    [
      33.69921,
      -117.91945
    ],
    [
      33.70197,
      -117.91946
    ],
    [
      33.70229,
      -117.91948
    ],
    [
      33.70791,
      -117.91957
    ],
    [
      33.71379,
      -117.91964
    ],
    [
      33.71396,
      -117.91963
    ],
    [
      33.71438,
      -117.91967
    ],
    [
      33.71478,
      -117.91978
    ],
    [
      33.71784,
      -117.921
    ],
    [
      33.71828,
      -117.92109
    ],
    [
      33.71871,
      -117.92109
    ],
    [
      33.71902,
      -117.92105
    ],
    [
      33.71928,
      -117.92098
    ],
    [
      33.71952,
      -117.92089
    ],
    [
      33.7197,
      -117.92079
    ],
    [
      33.72063,
      -117.92019
    ],
    [
      33.72104,
      -117.91997
    ],
    [
      33.72141,
      -117.91983
    ],
    [
      33.72172,
      -117.91976
    ],
    [
      33.72224,
      -117.91974
    ],
    [
      33.72648,
      -117.91978
    ],
    [
      33.72813,
      -117.91979
    ],
    [
      33.72813,
      -117.91974
    ],
    [
      33.72814,
      -117.91969
    ],
    [
      33.72759,
      -117.91969
    ],
    [
      33.72759,
      -117.91971
    ],
    [
      33.72755,
      -117.92008
    ],
    [
      33.7275,
      -117.92008
    ],
    [
      33.72739,
      -117.92009
    ],
    [
      33.7274,
      -117.9209
    ],
    [
      33.72742,
      -117.92119
    ],
    [
      33.72756,
      -117.92188
    ],
    [
      33.72769,
      -117.92229
    ],
    [
      33.72788,
      -117.9226
    ],
    [
      33.72807,
      -117.92296
    ],
    [
      33.72836,
      -117.92338
    ],
    [
      33.72841,
      -117.92356
    ],
    [
      33.72849,
      -117.92365
    ],
    [
      33.72917,
      -117.92424
    ],
    [
      33.72974,
      -117.92471
    ],
    [
      33.72985,
      -117.92472
    ],
    [
      33.73017,
      -117.92508
    ],
    [
      33.73042,
      -117.92547
    ],
    [
      33.73061,
      -117.92584
    ],
    [
      33.73085,
      -117.92648
    ],
    [
      33.73087,
      -117.92654
    ],
    [
      33.73084,
      -117.92672
    ],
    [
      33.73093,
      -117.92731
    ],
    [
      33.73096,
      -117.92827
    ],
    [
      33.73091,
      -117.9298
    ],
    [
      33.73097,
      -117.93005
    ],
    [
      33.73096,
      -117.93245
    ],
    [
      33.73092,
      -117.93257
    ],
    [
      33.73094,
      -117.93453
    ],
    [
      33.73093,
      -117.93459
    ],
    [
      33.73099,
      -117.93487
    ],
    [
      33.73097,
      -117.93701
    ],
    [
      33.73098,
      -117.9372
    ],
    [
      33.73049,
      -117.95499
    ],
    [
      33.73043,
      -117.96406
    ],
    [
      33.73043,
      -117.96415
    ],
    [
      33.73037,
      -117.9644
    ],
    [
      33.73036,
      -117.96541
    ],
    [
      33.73043,
      -117.96553
    ],
    [
      33.73039,
      -117.9701
    ],
    [
      33.73034,
      -117.97025
    ],
    [
      33.73032,
      -117.97094
    ],
    [
      33.73039,
      -117.97113
    ],
    [
      33.73038,
      -117.972
    ],
    [
      33.73039,
      -117.97221
    ],
    [
      33.73033,
      -117.97957
    ],
    [
      33.73032,
      -117.98365
    ],
    [
      33.73027,
      -117.98693
    ],
    [
      33.7303,
      -117.98869
    ],
    [
      33.73029,
      -117.99018
    ],
    [
      33.73026,
      -117.99541
    ],
    [
      33.73021,
      -117.99726
    ],
    [
      33.73019,
      -118.00028
    ],
    [
      33.73384,
      -118.00033
    ],
    [
      33.73407,
      -118.0003
    ],
    [
      33.73425,
      -118.00024
    ],
    [
      33.7345,
      -118.0001
    ],
    [
      33.73471,
      -117.99989
    ],
    [
      33.73509,
      -117.99949
    ],
    [
      33.73528,
      -117.99936
    ],
    [
      33.73537,
      -117.99931
    ],
    [
      33.73515,
      -117.99926
    ],
    [
      33.73499,
      -117.99916
    ],
    [
      33.73486,
      -117.99921
    ],
    [
      33.73474,
      -117.99924
    ],
    [
      33.73475,
      -117.99941
    ],
    [
      33.73474,
      -117.99924
    ],
    [
      33.73432,
      -117.9993
    ],
    [
      33.73377,
      -117.99929
    ],
    [
      33.73376,
      -118.00034
    ],
    [
      33.73019,
      -118.00028
    ],
    [
      33.73019,
      -118.00114
    ],
    [
      33.73013,
      -118.00132
    ],
    [
      33.7301,
      -118.00263
    ],
    [
      33.73017,
      -118.00274
    ],
    [
      33.73015,
      -118.00672
    ],
    [
      33.73008,
      -118.00703
    ],
    [
      33.73008,
      -118.00732
    ],
    [
      33.73017,
      -118.00732
    ],
    [
      33.73018,
      -118.00742
    ],
    [
      33.7302,
      -118.00742
    ],
    [
      33.7302,
      -118.0072
    ],
    [
      33.73032,
      -118.00711
    ],
    [
      33.73027,
      -118.00707
    ],
    [
      33.73022,
      -118.00711
    ],
    [
      33.73022,
      -118.00703
    ],
    [
      33.7302,
      -118.007
    ],
    [
      33.72994,
      -118.00699
    ],
    [
      33.72992,
      -118.00694
    ],
    [
      33.72992,
      -118.00664
    ],
    [
      33.72994,
      -118.00664
    ],
    [
      33.72995,
      -118.00662
    ],
    [
      33.73023,
      -118.00662
    ],
    [
      33.73023,
      -118.00661
    ],
    [
      33.73029,
      -118.00664
    ],
    [
      33.73067,
      -118.00666
    ],
    [
      33.73067,
      -118.00668
    ],
    [
      33.73067,
      -118.00681
    ],
    [
      33.73179,
      -118.00683
    ],
    [
      33.73186,
      -118.00674
    ],
    [
      33.73735,
      -118.00684
    ],
    [
      33.73806,
      -118.00683
    ],
    [
      33.73821,
      -118.00692
    ],
    [
      33.74179,
      -118.00698
    ],
    [
      33.74192,
      -118.0069
    ],
    [
      33.74369,
      -118.0069
    ],
    [
      33.74484,
      -118.0069
    ],
    [
      33.74713,
      -118.00704
    ],
    [
      33.74868,
      -118.007
    ],
    [
      33.74883,
      -118.00706
    ],
    [
      33.75808,
      -118.00716
    ],
    [
      33.75815,
      -118.00709
    ],
    [
      33.75836,
      -118.00708
    ],
    [
      33.75904,
      -118.00709
    ],
    [
      33.75919,
      -118.0071
    ],
    [
      33.75969,
      -118.0071
    ],
    [
      33.76134,
      -118.00712
    ],
    [
      33.76149,
      -118.0072
    ],
    [
      33.76267,
      -118.00724
    ],
    [
      33.76323,
      -118.00723
    ],
    [
      33.76331,
      -118.00721
    ],
    [
      33.76414,
      -118.00722
    ],
    [
      33.76426,
      -118.00725
    ],
    [
      33.7677,
      -118.0073
    ],
    [
      33.77098,
      -118.00736
    ],
    [
      33.77279,
      -118.00739
    ],
    [
      33.77286,
      -118.00732
    ],
    [
      33.77408,
      -118.00734
    ],
    [
      33.77446,
      -118.00739
    ],
    [
      33.77489,
      -118.00753
    ],
    [
      33.77517,
      -118.00768
    ],
    [
      33.77538,
      -118.00781
    ],
    [
      33.77571,
      -118.0081
    ],
    [
      33.77609,
      -118.00848
    ],
    [
      33.77632,
      -118.00884
    ],
    [
      33.77642,
      -118.00903
    ],
    [
      33.7765,
      -118.00934
    ],
    [
      33.77684,
      -118.00991
    ],
    [
      33.77722,
      -118.01038
    ],
    [
      33.77743,
      -118.01059
    ],
    [
      33.77779,
      -118.01084
    ],
    [
      33.77798,
      -118.01095
    ],
    [
      33.7783,
      -118.01107
    ],
    [
      33.77867,
      -118.01116
    ],
    [
      33.77902,
      -118.01119
    ],
    [
      33.78096,
      -118.01118
    ],
    [
      33.78106,
      -118.01116
    ],
    [
      33.78256,
      -118.01115
    ],
    [
      33.7861,
      -118.01115
    ],
    [
      33.79929,
      -118.01107
    ],
    [
      33.80356,
      -118.01103
    ],
    [
      33.80411,
      -118.01094
    ],
    [
      33.80523,
      -118.0107
    ],
    [
      33.80588,
      -118.01068
    ],
    [
      33.81991,
      -118.01084
    ],
    [
      33.82109,
      -118.01083
    ],
    [
      33.82269,
      -118.01087
    ],
    [
      33.83178,
      -118.01097
    ],
    [
      33.83185,
      -118.0109
    ],
    [
      33.84256,
      -118.01103
    ],
    [
      33.84382,
      -118.01102
    ],
    [
      33.84656,
      -118.01106
    ],
    [
      33.84824,
      -118.01109
    ],
    [
      33.852,
      -118.01112
    ],
    [
      33.85206,
      -118.01119
    ],
    [
      33.85236,
      -118.01119
    ],
    [
      33.85243,
      -118.01112
    ],
    [
      33.85502,
      -118.01114
    ],
    [
      33.85773,
      -118.01115
    ],
    [
      33.85838,
      -118.01116
    ],
    [
      33.85883,
      -118.01116
    ],
    [
      33.85884,
      -118.00973
    ],
    [
      33.85892,
      -118.00959
    ],
    [
      33.85896,
      -118.00403
    ],
    [
      33.85887,
      -118.00394
    ],
    [
      33.85889,
      -118.00248
    ],
    [
      33.85896,
      -118.0023
    ],
    [
      33.85898,
      -118.00055
    ],
    [
      33.85889,
      -118.00038
    ],
    [
      33.8589,
      -117.99967
    ],
    [
      33.85893,
      -117.99799
    ],
    [
      33.85895,
      -117.99389
    ],
    [
      33.85893,
      -117.99297
    ],
    [
      33.85898,
      -117.98896
    ],
    [
      33.85903,
      -117.9825
    ],
    [
      33.85904,
      -117.98129
    ],
    [
      33.85873,
      -117.98128
    ],
    [
      33.85873,
      -117.98113
    ],
    [
      33.85884,
      -117.98112
    ],
    [
      33.85886,
      -117.98102
    ],
    [
      33.85887,
      -117.97947
    ],
    [
      33.85884,
      -117.9794
    ],
    [
      33.85877,
      -117.97937
    ],
    [
      33.85871,
      -117.97937
    ],
    [
      33.85872,
      -117.98023
    ],
    [
      33.85857,
      -117.98024
    ],
    [
      33.85858,
      -117.9797
    ],
    [
      33.85851,
      -117.9797
    ],
    [
      33.85858,
      -117.9797
    ],
    [
      33.85858,
      -117.9805
    ],
    [
      33.85851,
      -117.9805
    ],
    [
      33.85843,
      -117.9805
    ],
    [
      33.85841,
      -117.98106
    ],
    [
      33.85846,
      -117.98133
    ],
    [
      33.85847,
      -117.98129
    ],
    [
      33.8585,
      -117.98128
    ],
    [
      33.85904,
      -117.98129
    ],
    [
      33.85908,
      -117.98115
    ],
    [
      33.85911,
      -117.9783
    ],
    [
      33.85912,
      -117.97636
    ],
    [
      33.85659,
      -117.97634
    ],
    [
      33.85659,
      -117.97618
    ],
    [
      33.85245,
      -117.97613
    ],
    [
      33.85051,
      -117.97611
    ],
    [
      33.85052,
      -117.97627
    ],
    [
      33.84934,
      -117.97626
    ],
    [
      33.84934,
      -117.9761
    ],
    [
      33.8481,
      -117.97608
    ],
    [
      33.84801,
      -117.97616
    ],
    [
      33.84685,
      -117.97615
    ],
    [
      33.84678,
      -117.98459
    ],
    [
      33.84682,
      -117.98513
    ],
    [
      33.8468,
      -117.98927
    ],
    [
      33.84678,
      -117.98934
    ],
    [
      33.84677,
      -117.98935
    ],
    [
      33.84678,
      -117.9894
    ],
    [
      33.84678,
      -117.99062
    ],
    [
      33.84675,
      -117.99538
    ],
    [
      33.84668,
      -117.99547
    ],
    [
      33.84667,
      -117.99631
    ],
    [
      33.84675,
      -117.99641
    ],
    [
      33.84674,
      -117.99784
    ],
    [
      33.84845,
      -117.99785
    ],
    [
      33.85167,
      -117.99787
    ],
    [
      33.85746,
      -117.99794
    ],
    [
      33.85943,
      -117.99801
    ],
    [
      33.8624,
      -117.99805
    ],
    [
      33.86498,
      -117.99807
    ],
    [
      33.86691,
      -117.99802
    ],
    [
      33.86737,
      -117.99802
    ],
    [
      33.86754,
      -117.99806
    ],
    [
      33.86868,
      -117.99812
    ],
    [
      33.87242,
      -117.99817
    ],
    [
      33.8781,
      -117.99821
    ],
    [
      33.879,
      -117.99823
    ],
    [
      33.87983,
      -117.99831
    ],
    [
      33.88061,
      -117.99831
    ],
    [
      33.88101,
      -117.99824
    ],
    [
      33.8814,
      -117.99807
    ],
    [
      33.88166,
      -117.9979
    ],
    [
      33.882,
      -117.99761
    ],
    [
      33.88281,
      -117.99672
    ],
    [
      33.88306,
      -117.99644
    ],
    [
      33.88338,
      -117.99617
    ],
    [
      33.88421,
      -117.99557
    ],
    [
      33.88453,
      -117.99535
    ],
    [
      33.88628,
      -117.99782
    ],
    [
      33.88661,
      -117.99822
    ],
    [
      33.88702,
      -117.99857
    ],
    [
      33.88759,
      -117.99891
    ],
    [
      33.88817,
      -117.99925
    ],
    [
      33.88816,
      -118.00386
    ],
    [
      33.88812,
      -118.01098
    ],
    [
      33.88818,
      -118.01106
    ],
    [
      33.88816,
      -118.01358
    ],
    [
      33.88811,
      -118.01386
    ],
    [
      33.88806,
      -118.01884
    ],
    [
      33.88804,
      -118.02145
    ],
    [
      33.88811,
      -118.02161
    ],
    [
      33.88809,
      -118.02255
    ],
    [
      33.8881,
      -118.02264
    ],
    [
      33.88803,
      -118.02275
    ],
    [
      33.88802,
      -118.02504
    ],
    [
      33.88807,
      -118.02529
    ],
    [
      33.88805,
      -118.02803
    ],
    [
      33.88807,
      -118.02819
    ],
    [
      33.88802,
      -118.03242
    ],
    [
      33.888,
      -118.03347
    ],
    [
      33.888,
      -118.03571
    ],
    [
      33.88791,
      -118.04625
    ],
    [
      33.88791,
      -118.04634
    ],
    [
      33.88789,
      -118.04633
    ],
    [
      33.88789,
      -118.04651
    ],
    [
      33.88855,
      -118.04649
    ],
    [
      33.89156,
      -118.04653
    ],
    [
      33.89358,
      -118.04649
    ],
    [
      33.89412,
      -118.04649
    ],
    [
      33.8961,
      -118.04656
    ],
    [
      33.89891,
      -118.04658
    ],
    [
      33.89891,
      -118.04654
    ],
    [
      33.899,
      -118.04655
    ],
    [
      33.89906,
      -118.04662
    ],
    [
      33.90236,
      -118.04663
    ],
    [
      33.90249,
      -118.04664
    ],
    [
      33.90242,
      -118.0581
    ],
    [
      33.90241,
      -118.05924
    ],
    [
      33.90241,
      -118.06013
    ],
    [
      33.90245,
      -118.06149
    ],
    [
      33.90242,
      -118.06398
    ],
    [
      33.90238,
      -118.06511
    ],
    [
      33.90226,
      -118.08244
    ],
    [
      33.90237,
      -118.08253
    ],
    [
      33.90586,
      -118.08259
    ],
    [
      33.90593,
      -118.08262
    ],
    [
      33.90598,
      -118.08266
    ],
    [
      33.90671,
      -118.08269
    ],
    [
      33.90679,
      -118.08261
    ],
    [
      33.90862,
      -118.08261
    ],
    [
      33.90901,
      -118.08254
    ],
    [
      33.9096,
      -118.08235
    ],
    [
      33.91056,
      -118.08195
    ],
    [
      33.91109,
      -118.08179
    ],
    [
      33.91146,
      -118.08175
    ],
    [
      33.91348,
      -118.08174
    ],
    [
      33.91704,
      -118.08175
    ],
    [
      33.91718,
      -118.08174
    ],
    [
      33.91716,
      -118.08189
    ],
    [
      33.91718,
      -118.0826
    ],
    [
      33.91717,
      -118.08312
    ],
    [
      33.91711,
      -118.08325
    ],
    [
      33.91711,
      -118.08877
    ],
    [
      33.91718,
      -118.08886
    ],
    [
      33.91718,
      -118.09483
    ],
    [
      33.9171,
      -118.09498
    ],
    [
      33.9171,
      -118.0979
    ],
    [
      33.91717,
      -118.09806
    ],
    [
      33.91717,
      -118.09934
    ],
    [
      33.91703,
      -118.0993
    ],
    [
      33.91687,
      -118.09933
    ],
    [
      33.91661,
      -118.09934
    ],
    [
      33.91661,
      -118.09923
    ],
    [
      33.91458,
      -118.09924
    ],
    [
      33.91454,
      -118.10117
    ],
    [
      33.9146,
      -118.10212
    ],
    [
      33.91456,
      -118.10352
    ],
    [
      33.91335,
      -118.10351
    ],
    [
      33.91333,
      -118.10397
    ],
    [
      33.91314,
      -118.10397
    ],
    [
      33.91314,
      -118.10402
    ],
    [
      33.91315,
      -118.10412
    ],
    [
      33.91256,
      -118.10414
    ],
    [
      33.91251,
      -118.10414
    ],
    [
      33.9125,
      -118.1039
    ],
    [
      33.91375,
      -118.10393
    ],
    [
      33.91382,
      -118.10401
    ],
    [
      33.91386,
      -118.10403
    ],
    [
      33.91387,
      -118.104
    ],
    [
      33.91408,
      -118.10448
    ],
    [
      33.9141,
      -118.10448
    ],
    [
      33.91393,
      -118.10585
    ],
    [
      33.9139,
      -118.10712
    ],
    [
      33.91392,
      -118.11027
    ],
    [
      33.9139,
      -118.11235
    ],
    [
      33.91387,
      -118.11474
    ],
    [
      33.91375,
      -118.1176
    ],
    [
      33.9133,
      -118.12373
    ],
    [
      33.9132,
      -118.12564
    ],
    [
      33.91313,
      -118.12792
    ],
    [
      33.91311,
      -118.13158
    ],
    [
      33.91312,
      -118.13801
    ],
    [
      33.91312,
      -118.14138
    ],
    [
      33.91308,
      -118.14462
    ],
    [
      33.91301,
      -118.14702
    ],
    [
      33.91279,
      -118.15045
    ],
    [
      33.91159,
      -118.16347
    ],
    [
      33.91123,
      -118.16749
    ],
    [
      33.91114,
      -118.16903
    ],
    [
      33.9111,
      -118.17093
    ],
    [
      33.91111,
      -118.17216
    ],
    [
      33.91114,
      -118.17287
    ],
    [
      33.91119,
      -118.17377
    ],
    [
      33.9113,
      -118.17463
    ],
    [
      33.91154,
      -118.17588
    ],
    [
      33.9118,
      -118.17684
    ],
    [
      33.91332,
      -118.1813
    ],
    [
      33.91431,
      -118.18433
    ],
    [
      33.91579,
      -118.18861
    ],
    [
      33.91632,
      -118.19011
    ],
    [
      33.91716,
      -118.19222
    ],
    [
      33.91875,
      -118.19587
    ],
    [
      33.91913,
      -118.19679
    ],
    [
      33.91982,
      -118.19838
    ],
    [
      33.9215,
      -118.20222
    ],
    [
      33.92505,
      -118.21017
    ],
    [
      33.9258,
      -118.2119
    ],
    [
      33.92622,
      -118.21291
    ],
    [
      33.92826,
      -118.21752
    ],
    [
      33.92872,
      -118.21862
    ],
    [
      33.929,
      -118.21939
    ],
    [
      33.92923,
      -118.22017
    ],
    [
      33.92945,
      -118.22111
    ],
    [
      33.92959,
      -118.22207
    ],
    [
      33.92968,
      -118.22306
    ],
    [
      33.92968,
      -118.22421
    ],
    [
      33.92958,
      -118.22537
    ],
    [
      33.92946,
      -118.2261
    ],
    [
      33.9293,
      -118.22686
    ],
    [
      33.92849,
      -118.23005
    ],
    [
      33.9283,
      -118.23085
    ],
    [
      33.9282,
      -118.2314
    ],
    [
      33.92812,
      -118.23208
    ],
    [
      33.92804,
      -118.2338
    ],
    [
      33.92824,
      -118.23706
    ],
    [
      33.92859,
      -118.24307
    ],
    [
      33.92879,
      -118.24663
    ],
    [
      33.92881,
      -118.24735
    ],
    [
      33.92877,
      -118.24833
    ],
    [
      33.92872,
      -118.24919
    ],
    [
      33.92837,
      -118.25209
    ],
    [
      33.92759,
      -118.25821
    ],
    [
      33.92754,
      -118.25894
    ],
    [
      33.92749,
      -118.26036
    ],
    [
      33.92751,
      -118.26448
    ],
    [
      33.9275,
      -118.26662
    ],
    [
      33.9275,
      -118.27008
    ],
    [
      33.92761,
      -118.2714
    ],
    [
      33.9282,
      -118.27452
    ],
    [
      33.9284,
      -118.2755
    ],
    [
      33.92872,
      -118.27742
    ],
    [
      33.9288,
      -118.27821
    ],
    [
      33.92881,
      -118.27907
    ],
    [
      33.92878,
      -118.28303
    ],
    [
      33.92873,
      -118.28476
    ],
    [
      33.92872,
      -118.28869
    ],
    [
      33.92873,
      -118.29157
    ],
    [
      33.92872,
      -118.29333
    ],
    [
      33.92864,
      -118.29449
    ],
    [
      33.92852,
      -118.29555
    ],
    [
      33.9283,
      -118.29679
    ],
    [
      33.9272,
      -118.30169
    ],
    [
      33.92699,
      -118.30234
    ],
    [
      33.9269,
      -118.30287
    ],
    [
      33.92596,
      -118.30708
    ],
    [
      33.92581,
      -118.30784
    ],
    [
      33.92559,
      -118.30933
    ],
    [
      33.92545,
      -118.3108
    ],
    [
      33.92539,
      -118.31221
    ],
    [
      33.92546,
      -118.32102
    ],
    [
      33.92543,
      -118.32238
    ],
    [
      33.92531,
      -118.32429
    ],
    [
      33.92524,
      -118.32515
    ],
    [
      33.92515,
      -118.32712
    ],
    [
      33.92511,
      -118.32758
    ],
    [
      33.925,
      -118.32985
    ],
    [
      33.92492,
      -118.33092
    ],
    [
      33.92486,
      -118.33196
    ],
    [
      33.92482,
      -118.33325
    ],
    [
      33.92487,
      -118.33418
    ],
    [
      33.925,
      -118.33512
    ],
    [
      33.92509,
      -118.33557
    ],
    [
      33.92524,
      -118.33621
    ],
    [
      33.92541,
      -118.33675
    ],
    [
      33.9257,
      -118.3375
    ],
    [
      33.92594,
      -118.33805
    ],
    [
      33.92616,
      -118.33849
    ],
    [
      33.92657,
      -118.33915
    ],
    [
      33.92801,
      -118.34118
    ],
    [
      33.93001,
      -118.34396
    ],
    [
      33.93056,
      -118.34479
    ],
    [
      33.93105,
      -118.34557
    ],
    [
      33.93186,
      -118.34708
    ],
    [
      33.93214,
      -118.34767
    ],
    [
      33.93255,
      -118.34872
    ],
    [
      33.93274,
      -118.34925
    ],
    [
      33.93305,
      -118.35033
    ],
    [
      33.9333,
      -118.35134
    ],
    [
      33.93346,
      -118.35215
    ],
    [
      33.93356,
      -118.35304
    ],
    [
      33.9336,
      -118.35392
    ],
    [
      33.93358,
      -118.35482
    ],
    [
      33.93353,
      -118.35529
    ],
    [
      33.9334,
      -118.35617
    ],
    [
      33.93321,
      -118.35707
    ],
    [
      33.93262,
      -118.35905
    ],
    [
      33.93189,
      -118.36143
    ],
    [
      33.93099,
      -118.36442
    ],
    [
      33.93075,
      -118.36524
    ],
    [
      33.93061,
      -118.36567
    ],
    [
      33.93024,
      -118.36711
    ],
    [
      33.93008,
      -118.36804
    ],
    [
      33.93,
      -118.3688
    ],
    [
      33.92999,
      -118.36927
    ],
    [
      33.92998,
      -118.37149
    ],
    [
      33.93002,
      -118.37189
    ],
    [
      33.93,
      -118.37416
    ],
    [
      33.92997,
      -118.3745
    ],
    [
      33.92974,
      -118.37551
    ],
    [
      33.92968,
      -118.37605
    ],
    [
      33.9297,
      -118.37721
    ],
    [
      33.92971,
      -118.3772
    ],
    [
      33.92972,
      -118.37797
    ],
    [
      33.92981,
      -118.37829
    ],
    [
      33.93,
      -118.37856
    ],
    [
      33.93028,
      -118.37873
    ],
    [
      33.93061,
      -118.37876
    ],
    [
      33.93505,
      -118.37867
    ],
    [
      33.93837,
      -118.37865
    ],
    [
      33.94358,
      -118.37868
    ],
    [
      33.94598,
      -118.37866
    ],
    [
      33.94809,
      -118.37866
    ],
    [
      33.94973,
      -118.37864
    ],
    [
      33.95006,
      -118.37864
    ],
    [
      33.95008,
      -118.37866
    ],
    [
      33.95062,
      -118.37818
    ],
    [
      33.95068,
      -118.37838
    ],
    [
      33.95068,
      -118.37842
    ],
    [
      33.95068,
      -118.37845
    ],
    [
      33.95059,
      -118.37844
    ],
    [
      33.95055,
      -118.37837
    ],
    [
      33.95055,
      -118.3779
    ],
    [
      33.95059,
      -118.37786
    ],
    [
      33.95115,
      -118.37782
    ],
    [
      33.95106,
      -118.37723
    ],
    [
      33.95068,
      -118.37738
    ],
    [
      33.94924,
      -118.37806
    ],
    [
      33.9487,
      -118.37828
    ],
    [
      33.94812,
      -118.37842
    ],
    [
      33.9471,
      -118.37849
    ],
    [
      33.94708,
      -118.37859
    ],
    [
      33.94713,
      -118.3787
    ],
    [
      33.9473,
      -118.37931
    ],
    [
      33.94735,
      -118.38
    ],
    [
      33.94736,
      -118.38261
    ],
    [
      33.94735,
      -118.38658
    ],
    [
      33.94736,
      -118.39386
    ],
    [
      33.94736,
      -118.39394
    ],
    [
      33.94872,
      -118.39394
    ],
    [
      33.94885,
      -118.39387
    ],
    [
      33.94918,
      -118.39396
    ],
    [
      33.94944,
      -118.39412
    ],
    [
      33.94959,
      -118.39429
    ],
    [
      33.94969,
      -118.39456
    ],
    [
      33.94973,
      -118.39483
    ],
    [
      33.9497,
      -118.39512
    ],
    [
      33.94912,
      -118.39781
    ],
    [
      33.94891,
      -118.39885
    ],
    [
      33.9488,
      -118.39919
    ],
    [
      33.94866,
      -118.39942
    ],
    [
      33.94848,
      -118.39956
    ],
    [
      33.9483,
      -118.39966
    ],
    [
      33.94791,
      -118.39973
    ],
    [
      33.94716,
      -118.3998
    ],
    [
      33.94573,
      -118.3998
    ],
    [
      33.94554,
      -118.39985
    ],
    [
      33.94552,
      -118.40068
    ],
    [
      33.94561,
      -118.40068
    ]
  ]
}