{
  "run_id": "run_97dac11aecb9",
  "day_index": 3,
  "markers": [
    {
      "lat": 33.5788371,
      "lng": 130.3935681,
      "name": "KKR 호텔 하카타"
    },
    {
      "lat": 33.5213697,
      "lng": 130.5348239,
      "name": "다자이후 텐만구 (太宰府天満宮)"
    },
    {
      "lat": 33.5190706,
      "lng": 130.5316571,
      "name": "一蘭 太宰府参道店 (이치란 다자이후 산도점)"
    },
    {
      "lat": 33.5883051,
      "lng": 130.4216938,
      "name": "요도바시 하카타 (ヨドバシ博多)"
    },
    {
      "lat": 33.5849988,
      "lng": 130.4490906,
      "name": "후쿠오카 공항"
    }
  ],
  "path": [
    [
      33.57873,
      130.39325
    ],
    [
      33.57819,
      130.3935
    ],
    [
      33.57815,
      130.39352
    ],
    [
      33.57816,
      130.39355
    ],
    [
      33.57843,
      130.3943
    ],
    [
      33.57874,
      130.39518
    ],
    [
      33.57893,
      130.39575
    ],
    [
      33.57893,
      130.39579
    ],
    [
      33.57887,
      130.39588
    ],
    [
      33.57897,
      130.39589
    ],
    [
      33.579,
      130.39594
    ],
    [
      33.57908,
      130.39619
    ],
    [
      33.5792,
      130.39652
    ],
    [
      33.57939,
      130.39707
    ],
    [
      33.57948,
      130.39729
    ],
    [
      33.57974,
      130.39803
    ],
    [
      33.57925,
      130.39833
    ],
    [
      33.57894,
      130.39853
    ],
    [
      33.57881,
      130.39864
    ],
    [
      33.57851,
      130.39892
    ],
    [
      33.57814,
      130.39937
    ],
    [
      33.57772,
      130.39988
    ],
    [
      33.57717,
      130.40058
    ],
    [
      33.57693,
      130.40089
    ],
    [
      33.57672,
      130.40117
    ],
    [
      33.57649,
      130.40147
    ],
    [
      33.57625,
      130.40176
    ],
    [
      33.57588,
      130.40223
    ],
    [
      33.57568,
      130.40249
    ],
    [
      33.57563,
      130.40253
    ],
    [
      33.57541,
      130.40285
    ],
    [
      33.57528,
      130.40304
    ],
    [
      33.57522,
      130.40312
    ],
    [
      33.57467,
      130.40391
    ],
    [
      33.57386,
      130.40503
    ],
    [
      33.57279,
      130.40647
    ],
    [
      33.57164,
      130.40804
    ],
    [
      33.5709,
      130.40902
    ],
    [
      33.57039,
      130.40972
    ],
    [
      33.5695,
      130.4109
    ],
    [
      33.56919,
      130.41131
    ],
    [
      33.56915,
      130.41134
    ],
    [
      33.56926,
      130.41145
    ],
    [
      33.56916,
      130.41158
    ],
    [
      33.56902,
      130.41176
    ],
    [
      33.56878,
      130.41206
    ],
    [
      33.56852,
      130.41234
    ],
    [
      33.56778,
      130.41311
    ],
    [
      33.56732,
      130.41363
    ],
    [
      33.56639,
      130.41468
    ],
    [
      33.56593,
      130.41518
    ],
    [
      33.5656,
      130.4155
    ],
    [
      33.56443,
      130.41677
    ],
    [
      33.56416,
      130.41706
    ],
    [
      33.56388,
      130.41738
    ],
    [
      33.56341,
      130.41789
    ],
    [
      33.56276,
      130.41866
    ],
    [
      33.56234,
      130.4192
    ],
    [
      33.56209,
      130.41952
    ],
    [
      33.56188,
      130.41984
    ],
    [
      33.5618,
      130.41998
    ],
    [
      33.56164,
      130.42026
    ],
    [
      33.56137,
      130.42086
    ],
    [
      33.56102,
      130.42166
    ],
    [
      33.56082,
      130.42208
    ],
    [
      33.56052,
      130.42263
    ],
    [
      33.56031,
      130.42294
    ],
    [
      33.56018,
      130.4231
    ],
    [
      33.56001,
      130.4233
    ],
    [
      33.55991,
      130.42341
    ],
    [
      33.55954,
      130.42375
    ],
    [
      33.55921,
      130.42403
    ],
    [
      33.55878,
      130.42429
    ],
    [
      33.55867,
      130.42439
    ],
    [
      33.55838,
      130.4245
    ],
    [
      33.55836,
      130.42462
    ],
    [
      33.55833,
      130.42472
    ],
    [
      33.55829,
      130.42479
    ],
    [
      33.55803,
      130.42503
    ],
    [
      33.55772,
      130.42533
    ],
    [
      33.55751,
      130.42557
    ],
    [
      33.55733,
      130.42583
    ],
    [
      33.55702,
      130.42629
    ],
    [
      33.55649,
      130.42705
    ],
    [
      33.55625,
      130.42742
    ],
    [
      33.55614,
      130.42761
    ],
    [
      33.55611,
      130.4277
    ],
    [
      33.55596,
      130.42813
    ],
    [
      33.55582,
      130.42855
    ],
    [
      33.55564,
      130.42914
    ],
    [
      33.55547,
      130.42974
    ],
    [
      33.55494,
      130.43169
    ],
    [
      33.55472,
      130.43251
    ],
    [
      33.55475,
      130.4327
    ],
    [
      33.55484,
      130.43281
    ],
    [
      33.55491,
      130.43288
    ],
    [
      33.55486,
      130.43293
    ],
    [
      33.55464,
      130.4334
    ],
    [
      33.55432,
      130.43413
    ],
    [
      33.55391,
      130.4351
    ],
    [
      33.55372,
      130.43556
    ],
    [
      33.55372,
      130.4356
    ],
    [
      33.55366,
      130.43569
    ],
    [
      33.55353,
      130.43592
    ],
    [
      33.55323,
      130.43641
    ],
    [
      33.55293,
      130.43677
    ],
    [
      33.55209,
      130.43773
    ],
    [
      33.55153,
      130.43839
    ],
    [
      33.55106,
      130.43893
    ],
    [
      33.55026,
      130.43996
    ],
    [
      33.5492,
      130.44136
    ],
    [
      33.5488,
      130.44187
    ],
    [
      33.5487,
      130.442
    ],
    [
      33.54869,
      130.44206
    ],
    [
      33.54861,
      130.44225
    ],
    [
      33.54848,
      130.44256
    ],
    [
      33.54833,
      130.44293
    ],
    [
      33.54816,
      130.44346
    ],
    [
      33.54804,
      130.44392
    ],
    [
      33.5479,
      130.44452
    ],
    [
      33.54788,
      130.44472
    ],
    [
      33.54785,
      130.44496
    ],
    [
      33.54782,
      130.44528
    ],
    [
      33.54763,
      130.44651
    ],
    [
      33.5475,
      130.44742
    ],
    [
      33.54737,
      130.44815
    ],
    [
      33.54729,
      130.44853
    ],
    [
      33.54712,
      130.44912
    ],
    [
      33.54672,
      130.45018
    ],
    [
      33.54639,
      130.45107
    ],
    [
      33.54621,
      130.45165
    ],
    [
      33.54598,
      130.45264
    ],
    [
      33.5459,
      130.45311
    ],
    [
      33.54586,
      130.45362
    ],
    [
      33.54585,
      130.45406
    ],
    [
      33.54591,
      130.45465
    ],
    [
      33.54599,
      130.4554
    ],
    [
      33.54605,
      130.45575
    ],
    [
      33.54614,
      130.45627
    ],
    [
      33.54614,
      130.45653
    ],
    [
      33.54611,
      130.45673
    ],
    [
      33.54599,
      130.4571
    ],
    [
      33.54586,
      130.45735
    ],
    [
      33.54579,
      130.45749
    ],
    [
      33.5453,
      130.4583
    ],
    [
      33.54469,
      130.4593
    ],
    [
      33.5446,
      130.45945
    ],
    [
      33.54456,
      130.46043
    ],
    [
      33.54451,
      130.46119
    ],
    [
      33.54449,
      130.46164
    ],
    [
      33.54451,
      130.4617
    ],
    [
      33.54446,
      130.46208
    ],
    [
      33.54444,
      130.46261
    ],
    [
      33.54435,
      130.46438
    ],
    [
      33.54431,
      130.46512
    ],
    [
      33.54425,
      130.46619
    ],
    [
      33.54418,
      130.46803
    ],
    [
      33.54416,
      130.46808
    ],
    [
      33.54414,
      130.46835
    ],
    [
      33.54414,
      130.4685
    ],
    [
      33.54414,
      130.4686
    ],
    [
      33.54408,
      130.46959
    ],
    [
      33.54406,
      130.47008
    ],
    [
      33.54401,
      130.47128
    ],
    [
      33.54401,
      130.47135
    ],
    [
      33.54347,
      130.47175
    ],
    [
      33.54278,
      130.47225
    ],
    [
      33.54117,
      130.47342
    ],
    [
      33.54066,
      130.47381
    ],
    [
      33.54039,
      130.47406
    ],
    [
      33.54013,
      130.47434
    ],
    [
      33.53975,
      130.47483
    ],
    [
      33.53926,
      130.47548
    ],
    [
      33.53896,
      130.47585
    ],
    [
      33.53888,
      130.47593
    ],
    [
      33.53861,
      130.4763
    ],
    [
      33.53843,
      130.47653
    ],
    [
      33.53811,
      130.47694
    ],
    [
      33.53803,
      130.47701
    ],
    [
      33.53779,
      130.47735
    ],
    [
      33.53766,
      130.47753
    ],
    [
      33.53762,
      130.47764
    ],
    [
      33.53748,
      130.47784
    ],
    [
      33.5373,
      130.47807
    ],
    [
      33.53696,
      130.47853
    ],
    [
      33.53665,
      130.47895
    ],
    [
      33.53628,
      130.47944
    ],
    [
      33.53614,
      130.47959
    ],
    [
      33.53607,
      130.47968
    ],
    [
      33.53594,
      130.47985
    ],
    [
      33.53589,
      130.47996
    ],
    [
      33.53576,
      130.48014
    ],
    [
      33.53553,
      130.48043
    ],
    [
      33.53534,
      130.48068
    ],
    [
      33.53478,
      130.48142
    ],
    [
      33.53458,
      130.4817
    ],
    [
      33.53435,
      130.482
    ],
    [
      33.5341,
      130.48231
    ],
    [
      33.53402,
      130.48244
    ],
    [
      33.53389,
      130.4826
    ],
    [
      33.53374,
      130.48282
    ],
    [
      33.5333,
      130.48341
    ],
    [
      33.53256,
      130.4844
    ],
    [
      33.53213,
      130.48495
    ],
    [
      33.53196,
      130.48514
    ],
    [
      33.53162,
      130.48551
    ],
    [
      33.53123,
      130.48595
    ],
    [
      33.53058,
      130.48666
    ],
    [
      33.53052,
      130.48673
    ],
    [
      33.53059,
      130.48682
    ],
    [
      33.53035,
      130.48708
    ],
    [
      33.52991,
      130.48755
    ],
    [
      33.52966,
      130.48779
    ],
    [
      33.5292,
      130.48829
    ],
    [
      33.52857,
      130.48901
    ],
    [
      33.52828,
      130.48941
    ],
    [
      33.52811,
      130.48969
    ],
    [
      33.52789,
      130.49021
    ],
    [
      33.52784,
      130.49034
    ],
    [
      33.52776,
      130.49069
    ],
    [
      33.52752,
      130.49155
    ],
    [
      33.52732,
      130.49204
    ],
    [
      33.52709,
      130.49245
    ],
    [
      33.52691,
      130.49268
    ],
    [
      33.52663,
      130.49304
    ],
    [
      33.52636,
      130.49333
    ],
    [
      33.52567,
      130.49416
    ],
    [
      33.52563,
      130.49422
    ],
    [
      33.52549,
      130.49441
    ],
    [
      33.52517,
      130.4948
    ],
    [
      33.5248,
      130.49526
    ],
    [
      33.52472,
      130.49541
    ],
    [
      33.52463,
      130.49546
    ],
    [
      33.52442,
      130.49573
    ],
    [
      33.52412,
      130.49607
    ],
    [
      33.5233,
      130.49706
    ],
    [
      33.52327,
      130.4971
    ],
    [
      33.52322,
      130.49703
    ],
    [
      33.52306,
      130.49721
    ],
    [
      33.52292,
      130.49741
    ],
    [
      33.52272,
      130.49766
    ],
    [
      33.52237,
      130.49805
    ],
    [
      33.52214,
      130.49829
    ],
    [
      33.52208,
      130.49838
    ],
    [
      33.52197,
      130.49842
    ],
    [
      33.52145,
      130.49882
    ],
    [
      33.52138,
      130.4989
    ],
    [
      33.521,
      130.49918
    ],
    [
      33.52074,
      130.49938
    ],
    [
      33.52041,
      130.49963
    ],
    [
      33.51968,
      130.50017
    ],
    [
      33.51935,
      130.50042
    ],
    [
      33.51921,
      130.50055
    ],
    [
      33.51871,
      130.50108
    ],
    [
      33.51848,
      130.50135
    ],
    [
      33.51833,
      130.50157
    ],
    [
      33.51812,
      130.50184
    ],
    [
      33.51779,
      130.50226
    ],
    [
      33.51762,
      130.50246
    ],
    [
      33.51707,
      130.50315
    ],
    [
      33.51646,
      130.50393
    ],
    [
      33.51637,
      130.504
    ],
    [
      33.51627,
      130.50413
    ],
    [
      33.51612,
      130.50433
    ],
    [
      33.51595,
      130.50451
    ],
    [
      33.51561,
      130.50492
    ],
    [
      33.51551,
      130.50501
    ],
    [
      33.51536,
      130.50522
    ],
    [
      33.51515,
      130.50552
    ],
    [
      33.5149,
      130.50586
    ],
    [
      33.51426,
      130.50667
    ],
    [
      33.51391,
      130.50716
    ],
    [
      33.51373,
      130.50747
    ],
    [
      33.51349,
      130.50783
    ],
    [
      33.51324,
      130.50806
    ],
    [
      33.51318,
      130.50809
    ],
    [
      33.5132,
      130.5082
    ],
    [
      33.5132,
      130.5084
    ],
    [
      33.51324,
      130.50888
    ],
    [
      33.51326,
      130.50941
    ],
    [
      33.51327,
      130.51087
    ],
    [
      33.51329,
      130.51216
    ],
    [
      33.5133,
      130.51334
    ],
    [
      33.51328,
      130.51354
    ],
    [
      33.51316,
      130.51419
    ],
    [
      33.51322,
      130.51421
    ],
    [
      33.51321,
      130.51426
    ],
    [
      33.5132,
      130.51442
    ],
    [
      33.51322,
      130.51488
    ],
    [
      33.51324,
      130.51507
    ],
    [
      33.51327,
      130.51522
    ],
    [
      33.51344,
      130.51583
    ],
    [
      33.51349,
      130.51603
    ],
    [
      33.51351,
      130.51622
    ],
    [
      33.51351,
      130.51652
    ],
    [
      33.51348,
      130.51816
    ],
    [
      33.51347,
      130.51862
    ],
    [
      33.51349,
      130.51988
    ],
    [
      33.51351,
      130.52141
    ],
    [
      33.51354,
      130.52266
    ],
    [
      33.51364,
      130.52414
    ],
    [
      33.51367,
      130.52448
    ],
    [
      33.51367,
      130.52516
    ],
    [
      33.51367,
      130.52594
    ],
    [
      33.51367,
      130.52618
    ],
    [
      33.51368,
      130.52638
    ],
    [
      33.51367,
      130.52673
    ],
    [
      33.51368,
      130.52714
    ],
    [
      33.51371,
      130.52743
    ],
    [
      33.51375,
      130.52771
    ],
    [
      33.51388,
      130.52801
    ],
    [
      33.51404,
      130.5283
    ],
    [
      33.51424,
      130.52857
    ],
    [
      33.51439,
      130.52871
    ],
    [
      33.51459,
      130.52886
    ],
    [
      33.51538,
      130.52934
    ],
    [
      33.51703,
      130.53032
    ],
    [
      33.51747,
      130.53059
    ],
    [
      33.51775,
      130.53072
    ],
    [
      33.51792,
      130.53078
    ],
    [
      33.51791,
      130.53086
    ],
    [
      33.518,
      130.53089
    ],
    [
      33.51839,
      130.531
    ],
    [
      33.51929,
      130.53124
    ],
    [
      33.5193,
      130.53142
    ],
    [
      33.51934,
      130.53149
    ],
    [
      33.51951,
      130.53152
    ],
    [
      33.51954,
      130.53152
    ],
    [
      33.51954,
      130.53166
    ],
    [
      33.51955,
      130.53195
    ],
    [
      33.51954,
      130.53288
    ],
    [
      33.51954,
      130.53429
    ],
    [
      33.52,
      130.53425
    ],
    [
      33.52072,
      130.53434
    ],
    [
      33.52084,
      130.53436
    ],
    [
      33.5208,
      130.53477
    ],
    [
      33.52085,
      130.53478
    ],
    [
      33.52131,
      130.53481
    ],
    [
      33.51908,
      130.53159
    ],
    [
      33.51954,
      130.53166
    ],
    [
      33.51954,
      130.53152
    ],
    [
      33.51948,
      130.53151
    ],
    [
      33.51933,
      130.53148
    ],
    [
      33.51929,
      130.53138
    ],
    [
      33.51929,
      130.53124
    ],
    [
      33.51908,
      130.53119
    ],
    [
      33.51816,
      130.53093
    ],
    [
      33.51773,
      130.5308
    ],
    [
      33.5176,
      130.53075
    ],
    [
      33.51762,
      130.53067
    ],
    [
      33.51747,
      130.53059
    ],
    [
      33.51703,
      130.53032
    ],
    [
      33.51579,
      130.52957
    ],
    [
      33.51459,
      130.52886
    ],
    [
      33.51439,
      130.52871
    ],
    [
      33.51424,
      130.52857
    ],
    [
      33.51404,
      130.5283
    ],
    [
      33.51388,
      130.52801
    ],
    [
      33.51375,
      130.52771
    ],
    [
      33.51368,
      130.52714
    ],
    [
      33.51367,
      130.52673
    ],
    [
      33.51368,
      130.52638
    ],
    [
      33.51367,
      130.52618
    ],
    [
      33.51367,
      130.52594
    ],
    [
      33.51367,
      130.52516
    ],
    [
      33.51367,
      130.52448
    ],
    [
      33.51364,
      130.52414
    ],
    [
      33.5136,
      130.52349
    ],
    [
      33.51354,
      130.52266
    ],
    [
      33.51351,
      130.52141
    ],
    [
      33.51349,
      130.51988
    ],
    [
      33.51347,
      130.51862
    ],
    [
      33.51348,
      130.51816
    ],
    [
      33.51351,
      130.51652
    ],
    [
      33.51351,
      130.51622
    ],
    [
      33.51349,
      130.51603
    ],
    [
      33.51344,
      130.51583
    ],
    [
      33.51327,
      130.51522
    ],
    [
      33.51324,
      130.51507
    ],
    [
      33.51322,
      130.51488
    ],
    [
      33.5132,
      130.51442
    ],
    [
      33.51321,
      130.51426
    ],
    [
      33.51322,
      130.51421
    ],
    [
      33.51316,
      130.51419
    ],
    [
      33.51318,
      130.51409
    ],
    [
      33.51328,
      130.51354
    ],
    [
      33.5133,
      130.51334
    ],
    [
      33.51329,
      130.51277
    ],
    [
      33.51328,
      130.51173
    ],
    [
      33.51327,
      130.51022
    ],
    [
      33.51326,
      130.50941
    ],
    [
      33.51324,
      130.50888
    ],
    [
      33.5132,
      130.5084
    ],
    [
      33.5132,
      130.5082
    ],
    [
      33.51318,
      130.50809
    ],
    [
      33.51324,
      130.50806
    ],
    [
      33.51336,
      130.50796
    ],
    [
      33.51349,
      130.50783
    ],
    [
      33.51361,
      130.50766
    ],
    [
      33.51391,
      130.50716
    ],
    [
      33.51452,
      130.50634
    ],
    [
      33.5149,
      130.50586
    ],
    [
      33.51515,
      130.50552
    ],
    [
      33.51536,
      130.50522
    ],
    [
      33.51551,
      130.50501
    ],
    [
      33.51561,
      130.50492
    ],
    [
      33.51595,
      130.50451
    ],
    [
      33.51612,
      130.50433
    ],
    [
      33.51627,
      130.50413
    ],
    [
      33.51637,
      130.504
    ],
    [
      33.51646,
      130.50393
    ],
    [
      33.51673,
      130.50358
    ],
    [
      33.51721,
      130.50298
    ],
    [
      33.51779,
      130.50226
    ],
    [
      33.51812,
      130.50184
    ],
    [
      33.51833,
      130.50157
    ],
    [
      33.51848,
      130.50135
    ],
    [
      33.51871,
      130.50108
    ],
    [
      33.51921,
      130.50055
    ],
    [
      33.51935,
      130.50042
    ],
    [
      33.51968,
      130.50017
    ],
    [
      33.52005,
      130.4999
    ],
    [
      33.52074,
      130.49938
    ],
    [
      33.521,
      130.49918
    ],
    [
      33.52138,
      130.4989
    ],
    [
      33.52145,
      130.49882
    ],
    [
      33.52165,
      130.49866
    ],
    [
      33.52197,
      130.49842
    ],
    [
      33.52208,
      130.49838
    ],
    [
      33.52214,
      130.49829
    ],
    [
      33.52237,
      130.49805
    ],
    [
      33.52272,
      130.49766
    ],
    [
      33.52292,
      130.49741
    ],
    [
      33.52306,
      130.49721
    ],
    [
      33.52322,
      130.49703
    ],
    [
      33.52327,
      130.4971
    ],
    [
      33.5233,
      130.49706
    ],
    [
      33.52339,
      130.49695
    ],
    [
      33.52397,
      130.49625
    ],
    [
      33.52412,
      130.49607
    ],
    [
      33.52442,
      130.49573
    ],
    [
      33.52463,
      130.49546
    ],
    [
      33.52472,
      130.49541
    ],
    [
      33.5248,
      130.49526
    ],
    [
      33.52492,
      130.49512
    ],
    [
      33.52517,
      130.4948
    ],
    [
      33.52549,
      130.49441
    ],
    [
      33.52563,
      130.49422
    ],
    [
      33.52567,
      130.49416
    ],
    [
      33.52636,
      130.49333
    ],
    [
      33.52663,
      130.49304
    ],
    [
      33.52709,
      130.49245
    ],
    [
      33.52732,
      130.49204
    ],
    [
      33.52752,
      130.49155
    ],
    [
      33.52776,
      130.49069
    ],
    [
      33.52784,
      130.49034
    ],
    [
      33.52789,
      130.49021
    ],
    [
      33.52811,
      130.48969
    ],
    [
      33.52828,
      130.48941
    ],
    [
      33.52857,
      130.48901
    ],
    [
      33.5292,
      130.48829
    ],
    [
      33.52966,
      130.48779
    ],
    [
      33.52991,
      130.48755
    ],
    [
      33.53035,
      130.48708
    ],
    [
      33.53042,
      130.48701
    ],
    [
      33.53045,
      130.48681
    ],
    [
      33.53058,
      130.48666
    ],
    [
      33.53123,
      130.48595
    ],
    [
      33.53148,
      130.48568
    ],
    [
      33.53187,
      130.48524
    ],
    [
      33.53229,
      130.48475
    ],
    [
      33.53359,
      130.48302
    ],
    [
      33.53388,
      130.48262
    ],
    [
      33.53405,
      130.4824
    ],
    [
      33.53452,
      130.48176
    ],
    [
      33.53474,
      130.48148
    ],
    [
      33.53571,
      130.48019
    ],
    [
      33.53589,
      130.47996
    ],
    [
      33.53598,
      130.47979
    ],
    [
      33.53621,
      130.4795
    ],
    [
      33.53634,
      130.47936
    ],
    [
      33.53663,
      130.47898
    ],
    [
      33.5369,
      130.4786
    ],
    [
      33.53743,
      130.4779
    ],
    [
      33.53762,
      130.47764
    ],
    [
      33.53774,
      130.47743
    ],
    [
      33.53803,
      130.47701
    ],
    [
      33.53811,
      130.47694
    ],
    [
      33.53829,
      130.4767
    ],
    [
      33.53845,
      130.4765
    ],
    [
      33.53866,
      130.47622
    ],
    [
      33.5389,
      130.47591
    ],
    [
      33.5392,
      130.47554
    ],
    [
      33.53941,
      130.47528
    ],
    [
      33.5397,
      130.4749
    ],
    [
      33.54007,
      130.47441
    ],
    [
      33.54037,
      130.47408
    ],
    [
      33.54076,
      130.47373
    ],
    [
      33.54147,
      130.4732
    ],
    [
      33.5423,
      130.4726
    ],
    [
      33.54314,
      130.47199
    ],
    [
      33.54396,
      130.47138
    ],
    [
      33.54585,
      130.47003
    ],
    [
      33.54615,
      130.46983
    ],
    [
      33.54686,
      130.46931
    ],
    [
      33.54776,
      130.46868
    ],
    [
      33.54805,
      130.46847
    ],
    [
      33.54827,
      130.4683
    ],
    [
      33.5489,
      130.46771
    ],
    [
      33.54934,
      130.46722
    ],
    [
      33.54969,
      130.46677
    ],
    [
      33.54986,
      130.46653
    ],
    [
      33.55013,
      130.4661
    ],
    [
      33.5503,
      130.46588
    ],
    [
      33.55089,
      130.46518
    ],
    [
      33.55107,
      130.46499
    ],
    [
      33.55112,
      130.4649
    ],
    [
      33.55136,
      130.46468
    ],
    [
      33.55157,
      130.46454
    ],
    [
      33.55158,
      130.46448
    ],
    [
      33.55168,
      130.4638
    ],
    [
      33.55204,
      130.46136
    ],
    [
      33.5522,
      130.46028
    ],
    [
      33.55243,
      130.45874
    ],
    [
      33.55253,
      130.45877
    ],
    [
      33.55264,
      130.45801
    ],
    [
      33.5527,
      130.4577
    ],
    [
      33.55277,
      130.45713
    ],
    [
      33.55285,
      130.45662
    ],
    [
      33.55289,
      130.45643
    ],
    [
      33.55294,
      130.45609
    ],
    [
      33.55318,
      130.45582
    ],
    [
      33.5532,
      130.45577
    ],
    [
      33.5535,
      130.45545
    ],
    [
      33.55396,
      130.45503
    ],
    [
      33.55454,
      130.45451
    ],
    [
      33.55475,
      130.45433
    ],
    [
      33.55525,
      130.45388
    ],
    [
      33.5554,
      130.45374
    ],
    [
      33.55563,
      130.45352
    ],
    [
      33.55583,
      130.4533
    ],
    [
      33.55591,
      130.45319
    ],
    [
      33.55599,
      130.45313
    ],
    [
      33.55608,
      130.45303
    ],
    [
      33.55612,
      130.45295
    ],
    [
      33.55733,
      130.45165
    ],
    [
      33.55753,
      130.45143
    ],
    [
      33.55817,
      130.45075
    ],
    [
      33.55925,
      130.44957
    ],
    [
      33.55979,
      130.44897
    ],
    [
      33.56015,
      130.4486
    ],
    [
      33.5603,
      130.44844
    ],
    [
      33.5605,
      130.44823
    ],
    [
      33.5607,
      130.44797
    ],
    [
      33.56167,
      130.44691
    ],
    [
      33.5616,
      130.44682
    ],
    [
      33.56162,
      130.44679
    ],
    [
      33.56191,
      130.44647
    ],
    [
      33.56303,
      130.44524
    ],
    [
      33.56328,
      130.44496
    ],
    [
      33.56336,
      130.44487
    ],
    [
      33.56357,
      130.44462
    ],
    [
      33.5639,
      130.44425
    ],
    [
      33.56419,
      130.44393
    ],
    [
      33.56522,
      130.44279
    ],
    [
      33.56688,
      130.44096
    ],
    [
      33.56743,
      130.44033
    ],
    [
      33.56768,
      130.44007
    ],
    [
      33.5681,
      130.4396
    ],
    [
      33.56853,
      130.43913
    ],
    [
      33.56879,
      130.4389
    ],
    [
      33.56908,
      130.43872
    ],
    [
      33.56929,
      130.43862
    ],
    [
      33.56955,
      130.4385
    ],
    [
      33.56971,
      130.43846
    ],
    [
      33.57046,
      130.43833
    ],
    [
      33.57141,
      130.43815
    ],
    [
      33.57214,
      130.43803
    ],
    [
      33.57343,
      130.4378
    ],
    [
      33.57365,
      130.43774
    ],
    [
      33.57413,
      130.43755
    ],
    [
      33.57456,
      130.43731
    ],
    [
      33.57481,
      130.43715
    ],
    [
      33.57528,
      130.43676
    ],
    [
      33.57557,
      130.4365
    ],
    [
      33.57727,
      130.43503
    ],
    [
      33.57798,
      130.43442
    ],
    [
      33.57826,
      130.43414
    ],
    [
      33.5789,
      130.43337
    ],
    [
      33.57905,
      130.43318
    ],
    [
      33.58085,
      130.43095
    ],
    [
      33.58222,
      130.42924
    ],
    [
      33.58411,
      130.42688
    ],
    [
      33.58672,
      130.42362
    ],
    [
      33.58725,
      130.42294
    ],
    [
      33.58733,
      130.42284
    ],
    [
      33.58737,
      130.42277
    ],
    [
      33.5874,
      130.42266
    ],
    [
      33.5874,
      130.42252
    ],
    [
      33.58741,
      130.42238
    ],
    [
      33.58736,
      130.42215
    ],
    [
      33.58761,
      130.42218
    ],
    [
      33.58762,
      130.4219
    ],
    [
      33.58764,
      130.42156
    ],
    [
      33.58764,
      130.42139
    ],
    [
      33.58765,
      130.42124
    ],
    [
      33.58805,
      130.42132
    ],
    [
      33.58833,
      130.42136
    ]
  ]
}